{
  "name": "SYS · Session Duration by User & Day",
  "sql": "WITH user_activity AS (\n    SELECT \n        jsonb_extract_path_text(value::jsonb, 'username') AS username,\n        date_created,\n        type,\n        value\n    FROM events\n    WHERE type IN ('USER_LOGIN', 'PAGE_VIEW')\n),\nsession_start_end AS (\n    SELECT \n        username,\n        DATE(date_created) AS session_date,\n        date_created AS session_start,\n        LEAD(date_created) OVER (\n            PARTITION BY username, DATE(date_created)\n            ORDER BY date_created\n        ) AS session_end,\n        value\n    FROM user_activity\n    WHERE type = 'USER_LOGIN'\n)\nSELECT \n    s.session_date,\n    s.username,\n    s.session_start AS login_time,\n    MAX(pv.date_created) AS last_page_viewed_time,\n    FLOOR(EXTRACT(EPOCH FROM (COALESCE(s.session_end, MAX(pv.date_created)) - s.session_start)) / 60) AS total_session_minutes\nFROM session_start_end s\nJOIN user_activity pv\n    ON s.username = pv.username\n    AND DATE(s.session_start) = DATE(pv.date_created)\n    AND pv.date_created > s.session_start\n    AND pv.type = 'PAGE_VIEW' -- Only consider PAGE_VIEW events after login\nGROUP BY s.session_date, s.username, s.session_start, s.session_end\nORDER BY s.session_date, s.username, s.session_start\n",
  "json_data": {
    "column_types": {}
  },
  "tags": [
    "system",
    "telemetry"
  ],
  "default_params": [],
  "id": "a6f2ec31-d416-4f8d-bb36-ad7daaed6c47",
  "columns": [
    {
      "name": "session_date",
      "type_code": 1082,
      "display_size": null,
      "internal_size": 4,
      "precision": null,
      "scale": null,
      "null_ok": null,
      "type": "DATE"
    },
    {
      "name": "username",
      "type_code": 25,
      "display_size": null,
      "internal_size": -1,
      "precision": null,
      "scale": null,
      "null_ok": null,
      "type": "TEXT"
    },
    {
      "name": "login_time",
      "type_code": 1184,
      "display_size": null,
      "internal_size": 8,
      "precision": null,
      "scale": null,
      "null_ok": null,
      "type": "TIMESTAMPTZ"
    },
    {
      "name": "last_page_viewed_time",
      "type_code": 1184,
      "display_size": null,
      "internal_size": 8,
      "precision": null,
      "scale": null,
      "null_ok": null,
      "type": "TIMESTAMPTZ"
    },
    {
      "name": "total_session_minutes",
      "type_code": 701,
      "display_size": null,
      "internal_size": 8,
      "precision": null,
      "scale": null,
      "null_ok": null,
      "type": "FLOAT(8)"
    }
  ],
  "updated_at": "2026-06-29T16:07:44.640467Z",
  "created_at": "2024-06-06T18:33:56.913986Z",
  "error": null,
  "database_connection": null
}
